{
  "name": "Astronaut",
  "scale": 0.4,
  "shapes": [
	{ "type": "Persegi", "x": 561, "y": 244, "angle": 0 },
	{ "type": "Persegi", "x": 533, "y": 244, "angle": 0 },
	{ "type": "Persegi", "x": 561, "y": 272, "angle": 0 },
	{ "type": "Persegi", "x": 533, "y": 272, "angle": 0 },
	{ "type": "Persegi", "x": 561, "y": 300, "angle": 0 },
	{ "type": "Persegi", "x": 561, "y": 328, "angle": 0 },
	{ "type": "Persegi", "x": 533, "y": 328, "angle": 0 },
	{ "type": "Persegi", "x": 590, "y": 328, "angle": 0 },
	{ "type": "Persegi", "x": 590, "y": 300, "angle": 0 },
	{ "type": "Persegi", "x": 590, "y": 272, "angle": 0 },
	{ "type": "Persegi", "x": 590, "y": 244, "angle": 0 },
	{ "type": "Persegi", "x": 618, "y": 244, "angle": 0 },
	{ "type": "Persegi", "x": 618, "y": 272, "angle": 0 },
	{ "type": "Persegi", "x": 618, "y": 300, "angle": 0 },
	{ "type": "Persegi", "x": 618, "y": 328, "angle": 0 },
	{ "type": "Jajar Genjang", "x": 625, "y": 353, "angle": -60 },
	{ "type": "Jajar Genjang", "x": 526, "y": 354, "angle": 0 },
	{ "type": "Jajar Genjang", "x": 597, "y": 354, "angle": -60 },
	{ "type": "Segitiga", "x": 576, "y": 353, "angle": 0 },
	{ "type": "Jajar Genjang", "x": 553, "y": 354, "angle": 0 },
	{ "type": "Jajar Genjang", "x": 540, "y": 378, "angle": 0 },
	{ "type": "Jajar Genjang", "x": 512, "y": 378, "angle": 0 },
	{ "type": "Persegi", "x": 506, "y": 432, "angle": 0 },
	{ "type": "Persegi", "x": 534, "y": 432, "angle": 0 },
	{ "type": "Persegi", "x": 506, "y": 404, "angle": 0 },
	{ "type": "Persegi", "x": 534, "y": 404, "angle": 0 },
	{ "type": "Trapesium", "x": 506, "y": 459, "angle": 0 },
	{ "type": "Jajar Genjang", "x": 471, "y": 458, "angle": 0 },
	{ "type": "Segitiga", "x": 538, "y": 452, "angle": -60 },
	{ "type": "Persegi", "x": 632, "y": 380, "angle": 0 },
	{ "type": "Persegi", "x": 604, "y": 380, "angle": 0 },
	{ "type": "Persegi", "x": 604, "y": 408, "angle": 0 },
	{ "type": "Persegi", "x": 632, "y": 408, "angle": 0 },
	{ "type": "Persegi", "x": 604, "y": 436, "angle": 0 },
	{ "type": "Persegi", "x": 632, "y": 436, "angle": 0 },
	{ "type": "Trapesium", "x": 604, "y": 462, "angle": 0 },
	{ "type": "Segitiga", "x": 635, "y": 456, "angle": -60 },
	{ "type": "Jajar Genjang", "x": 596, "y": 486, "angle": -60 },
	{ "type": "Jajar Genjang", "x": 568, "y": 486, "angle": -60 },
	{ "type": "Segitiga", "x": 621, "y": 480, "angle": -60 },
	{ "type": "Segitiga", "x": 533, "y": 217, "angle": 0 },
	{ "type": "Jajar Genjang", "x": 555, "y": 217, "angle": -60 },
	{ "type": "Belah Ketupat", "x": 639, "y": 284, "angle": -60 },
	{ "type": "Jajar Genjang", "x": 652, "y": 271, "angle": -60 },
	{ "type": "Jajar Genjang", "x": 680, "y": 271, "angle": -60 },
	{ "type": "Jajar Genjang", "x": 695, "y": 295, "angle": -60 },
	{ "type": "Jajar Genjang", "x": 667, "y": 295, "angle": -60 },
	{ "type": "Jajar Genjang", "x": 667, "y": 320, "angle": 0 },
	{ "type": "Jajar Genjang", "x": 695, "y": 320, "angle": 0 },
	{ "type": "Persegi", "x": 660, "y": 346, "angle": 0 },
	{ "type": "Persegi", "x": 688, "y": 346, "angle": 0 },
	{ "type": "Trapesium", "x": 500, "y": 254, "angle": -149 },
	{ "type": "Persegi", "x": 533, "y": 300, "angle": 0 },
	{ "type": "Segitiga", "x": 512, "y": 268, "angle": -30 },
	{ "type": "Jajar Genjang", "x": 469, "y": 272, "angle": -30 },
	{ "type": "Jajar Genjang", "x": 494, "y": 286, "angle": -30 },
	{ "type": "Persegi", "x": 450, "y": 291, "angle": -30 },
	{ "type": "Persegi", "x": 436, "y": 315, "angle": -30 },
	{ "type": "Persegi", "x": 475, "y": 304, "angle": -30 },
	{ "type": "Jajar Genjang", "x": 583, "y": 216, "angle": -60 },
	{ "type": "Jajar Genjang", "x": 611, "y": 217, "angle": -60 },
	{ "type": "Trapesium", "x": 659, "y": 246, "angle": 0 },
	{ "type": "Belah Ketupat", "x": 638, "y": 232, "angle": 90 },
	{ "type": "Persegi", "x": 659, "y": 220, "angle": 0 },
	{ "type": "Persegi", "x": 645, "y": 166, "angle": 0 },
	{ "type": "Trapesium", "x": 635, "y": 199, "angle": 60 },
	{ "type": "Jajar Genjang", "x": 638, "y": 139, "angle": 120 },
	{ "type": "Jajar Genjang", "x": 624, "y": 115, "angle": 120 },
	{ "type": "Segitiga", "x": 602, "y": 115, "angle": 0 },
	{ "type": "Trapesium", "x": 574, "y": 115, "angle": -180 },
	{ "type": "Segitiga", "x": 545, "y": 115, "angle": 0 },
	{ "type": "Persegi", "x": 504, "y": 167, "angle": 0 },
	{ "type": "Trapesium", "x": 515, "y": 199, "angle": -60 },
	{ "type": "Jajar Genjang", "x": 524, "y": 115, "angle": 0 },
	{ "type": "Hexagon", "x": 577, "y": 180, "angle": 90 },
	{ "type": "Jajar Genjang", "x": 510, "y": 139, "angle": 0 }
  ]
}
